ixmachina/__init__.py
ixmachina/format_output.py
ixmachina/agent/__init__.py
ixmachina/agent/agent.py
ixmachina/agent/base_agent.py
ixmachina/agent/save_objects.py
ixmachina/agent/verbose.py
ixmachina/llm/__init__.py
ixmachina/llm/env_var.py
ixmachina/llm/llm.py
ixmachina/llm/query_anthropic.py
ixmachina/llm/query_openai.py
ixmachina/llm/tools.py
ixmachina/llm/tools_openai.py
ixmachina/memory/__init__.py
ixmachina/memory/embeddings.py
ixmachina/memory/fact.py
ixmachina/memory/memory_object.py
ixmachina/memory/memory_store.py
ixmachina/tools/__init__.py
ixmachina/tools/data/__init__.py
ixmachina/tools/file_system/__init__.py
ixmachina/tools/file_system/compare_dirs.py
ixmachina/tools/file_system/compare_files.py
ixmachina/tools/file_system/delete_dir.py
ixmachina/tools/file_system/delete_file.py
ixmachina/tools/file_system/empty_dir.py
ixmachina/tools/file_system/empty_recycle_bin.py
ixmachina/tools/file_system/get_file_status.py
ixmachina/tools/file_system/list_dir.py
ixmachina/tools/file_system/list_dir_contents.py
ixmachina/tools/file_system/memory.py
ixmachina/tools/file_system/path_utils.py
ixmachina/tools/file_system/recycle_bin.py
ixmachina/tools/file_system/undelete.py
ixmachina/tools/file_system/copy_move/__init__.py
ixmachina/tools/file_system/copy_move/change_dir_path.py
ixmachina/tools/file_system/copy_move/change_file_path.py
ixmachina/tools/file_system/copy_move/change_path.py
ixmachina/tools/file_system/copy_move/clone_dir_to_path.py
ixmachina/tools/file_system/copy_move/clone_file_to_path.py
ixmachina/tools/file_system/copy_move/clone_to_path.py
ixmachina/tools/file_system/copy_move/copy_dir_into.py
ixmachina/tools/file_system/copy_move/copy_file_into.py
ixmachina/tools/file_system/copy_move/copy_into.py
ixmachina/tools/file_system/copy_move/move_dir_into.py
ixmachina/tools/file_system/copy_move/move_file_into.py
ixmachina/tools/file_system/copy_move/move_into.py
ixmachina/tools/pricing/__init__.py
ixmachina/tools/pricing/get_model_prices.py
ixmachina-0.1.0.dist-info/METADATA
ixmachina-0.1.0.dist-info/WHEEL
ixmachina-0.1.0.dist-info/top_level.txt
ixmachina-0.1.0.dist-info/RECORD
